[
  { "id": 1, "title": "La Llegada", "tags": ["ciencia ficcion", "suspenso"] },
  { "id": 2, "title": "El Pianista", "tags": ["violento", "drama"] },
  {
    "id": 3,
    "title": "Ghost in the Shell",
    "tags": ["anime", "ciberpunk", "ciencia ficcion"]
  },
  { "id": 4, "title": "Scarface", "tags": ["violento", "drama"] },
  {
    "id": 4321865,
    "title": "peli de la terminal 4321865",
    "tags": ["rr", "ww"]
  },
  { "id": 139264, "title": "title 142556139264", "tags": ["tt", "rr"] },
  { "id": 213636, "title": "title 142556213636", "tags": ["yy", "uu"] },
  { "id": 207188, "title": "title 139803207188", "tags": ["tt", "rr"] },
  { "id": 134163, "title": "title 139803134163", "tags": ["yy", "uu"] },
  {
    "id": 212645,
    "title": "una peli 212645",
    "tags": ["classic", "tag 212645"]
  },
  {
    "id": 176993,
    "title": "otra peli un poco más divertida",
    "tags": ["tag 212645"]
  },
  { "id": 188388, "title": "title 147335188388", "tags": ["tt", "rr"] },
  { "id": 203935, "title": "title 147335203935", "tags": ["yy", "uu"] },
  { "id": 172265, "title": "title 183819172265", "tags": ["tt", "rr"] },
  { "id": 157493, "title": "title 183819157493", "tags": ["yy", "uu"] },
  {
    "id": 168250,
    "title": "una peli 168250",
    "tags": ["classic", "tag 168250"]
  },
  {
    "id": 183426,
    "title": "otra peli un poco más divertida",
    "tags": ["tag 168250"]
  },
  { "id": 180981, "title": "title 184934180981", "tags": ["tt", "rr"] },
  { "id": 220787, "title": "title 184934220787", "tags": ["yy", "uu"] },
  { "id": 193831, "title": "title 160923193831", "tags": ["tt", "rr"] },
  { "id": 147313, "title": "title 160923147313", "tags": ["yy", "uu"] },
  {
    "id": 193371,
    "title": "una peli 193371",
    "tags": ["classic", "tag 193371"]
  },
  {
    "id": 150622,
    "title": "otra peli un poco más divertida",
    "tags": ["tag 193371"]
  },
  { "id": 161937, "title": "title 194230161937", "tags": ["tt", "rr"] },
  { "id": 197574, "title": "title 194230197574", "tags": ["yy", "uu"] },
  { "id": 205962, "title": "title 159368205962", "tags": ["tt", "rr"] },
  { "id": 148349, "title": "title 159368148349", "tags": ["yy", "uu"] },
  {
    "id": 135801,
    "title": "una peli 135801",
    "tags": ["classic", "tag 135801"]
  },
  {
    "id": 142682,
    "title": "otra peli un poco más divertida",
    "tags": ["tag 135801"]
  },
  { "id": 159816, "title": "title 227764159816", "tags": ["tt", "rr"] },
  { "id": 158232, "title": "title 227764158232", "tags": ["yy", "uu"] },
  { "id": 178313, "title": "title 205742178313", "tags": ["tt", "rr"] },
  { "id": 150048, "title": "title 205742150048", "tags": ["yy", "uu"] },
  {
    "id": 132259,
    "title": "una peli 132259",
    "tags": ["classic", "tag 132259"]
  },
  {
    "id": 168731,
    "title": "otra peli un poco más divertida",
    "tags": ["tag 132259"]
  },
  {
    "id": 4411,
    "title": "Título de la nueva peli",
    "tags": ["action", "classic"]
  }
]
