[{"id":1,"title":"El padrino","tags":["crimen","drama"]},{"id":2,"title":"Vengadores:Infinity War","tags":["aventura","accion","fantasia"]},{"id":3,"title":"Regreso al futuro","tags":["ciencia ficcion","aventura","favorita"]},{"id":4,"title":"Forrest gump","tags":["romantico","drama","favorita"]},{"id":4411,"title":"Título de la nueva peli","tags":["action","classic"]},{"id":150150,"title":"Peli nueva","tags":["crimen","drama"]},{"id":1515,"title":"Peli nueva","tags":["crimen","drama"]},{"id":15150,"title":"Peli nueva","tags":["crimen","drama"]}]
