[{"id":123,"title":"Juego de Gemelas","tags":["familia","comedia","disney"]},{"id":456,"title":"Frozen","tags":["favorita","disney","animacion"]},{"id":321,"title":"aaa","tags":["animacion","comedia","familia"]},{"id":654,"title":"New York Minute","tags":["familia","comedia","romance"]},{"id":987,"title":"A walk to remember","tags":["familia","romance","drama"]},{"id":4411,"title":"Título de la nueva peli","tags":["action","classic"]},{"id":4321865,"title":"peli de la terminal 4321865","tags":["rr","ww"]},{"id":158564,"title":"title 163547158564","tags":["tt","rr"]},{"id":140115,"title":"title 163547140115","tags":["yy","uu"]},{"id":888,"title":"Prueba"}]
