[{"id":1,"title":"Batman Begins","rating":8.2,"tags":["acción","superhéroes","batman"]},{"id":2,"title":"Top Gun: Maverick","rating":8.5,"tags":["acción","aviones","militar"]},{"id":3,"title":"The Dark Knight","rating":9,"tags":["acción","superhéroes","batman"]},{"id":4,"title":"The Dark Knight Rises","rating":8.4,"tags":["acción","superhéroes","batman"]},{"id":5,"title":"Inception","rating":8.8,"tags":["acción","aventura","ciencia ficción"]},{"id":6,"title":"Interestellar","rating":8.6,"tags":["aventura","drama","ciencia ficción","espacio"]},{"id":7,"title":"Fight Club","rating":8.8,"tags":["drama","comedia negra","suspenso"]},{"id":8,"title":"Django Unchained","rating":8.4,"tags":["drama","acción","western"]},{"id":9,"title":"Inglourious Basterds","rating":8.3,"tags":["aventura","drama","belico","militar","comedia negra","sangrienta"]},{"id":10,"title":"Forrest Gump","rating":8.8,"tags":["drama","romance","comedia","familiar"]},{"id":11,"title":"The Green Mile","rating":8.6,"tags":["crimen","drama","fantasía","triste"]},{"id":12,"title":"Gladiator","rating":8.5,"tags":["acción","aventura","drama","roma","edad media"]},{"id":13,"title":"The Matrix","rating":8.7,"tags":["acción","ciencia ficción","cyberpunk"]},{"id":14,"title":"Matrix Reloaded","rating":7.2,"tags":["acción","ciencia ficción","cyberpunk"]},{"id":15,"title":"Matrix Revolutions","rating":6.7,"tags":["acción","ciencia ficción","cyberpunk"]},{"id":16,"title":"Constantine","rating":7,"tags":["acción","fantasía","terror","demonios","religion"]},{"id":17,"title":"Van Helsing","rating":6,"tags":["acción","aventura","fantasía","terror","mounstros","suspenso","vampiros","hombres lobo"]},{"id":18,"title":"GoldenEye","rating":7.2,"tags":["acción","aventura","suspenso","espionaje","agente secreto","James Bond","007"]},{"id":19,"title":"Tomorrow Never Dies","rating":6.5,"tags":["acción","aventura","suspenso","espionaje","agente secreto","James Bond","007"]},{"id":20,"title":"The Lord of the Rings: The Fellowship of the Ring","rating":8.8,"tags":["acción","aventura","drama","fantasía medieval","oscura"]},{"id":21,"title":"The Lord of the Rings: The Two Towers","rating":8.8,"tags":["acción","aventura","drama","fantasía medieval","oscura"]},{"id":22,"title":"The Lord of the Rings: The Return of the King","rating":9,"tags":["acción","aventura","drama","fantasía medieval","oscura"]},{"id":23,"title":"The Hobbit: An Unexpected Journey","rating":7.8,"tags":["acción","aventura","drama","fantasía medieval","oscura"]},{"id":24,"title":"Pirates of the Caribbean: The Curse of the Black Pearl","rating":8.1,"tags":["acción","aventura","fantasía oscura","piratas","naval"]},{"id":25,"title":"La vita è bella","rating":8.6,"tags":["comedia","drama","segunda guerra mundial","holocausto","familiar","italiano"]},{"id":26,"title":"Intouchables","rating":8.5,"tags":["biografia","comedia","drama","amistad","comedia dramática","familiar","francés"]},{"id":27,"title":"Pinocchio","rating":5.1,"tags":["aventura","comedia","drama","infantil","cuento de hadas","familiar"]},{"id":28,"title":"Lightyear","rating":5.9,"tags":["animación","acción","aventura","ciencia ficción","espacio","familiar"]},{"id":29,"title":"Soju Senshi Psychic Wars","rating":3.4,"tags":["animé","acción","aventura","japonés"]},{"id":30,"title":"Cats","rating":2.8,"tags":["comedia","drama","familiar"]},{"id":31,"title":"Serbia campeón Qatar 2022: La Película","rating":9.6,"tags":["acción","drama","deporte","futbol","superheroes","terror psicológico"]},{"id":4321865,"title":"peli de la terminal 4321865","rating":4.5,"tags":["cción,dram"]}]
